LICENSE
LICENSE_weights
README.md
setup.py
src/muq/__init__.py
src/muq.egg-info/PKG-INFO
src/muq.egg-info/SOURCES.txt
src/muq.egg-info/dependency_links.txt
src/muq.egg-info/requires.txt
src/muq.egg-info/top_level.txt
src/muq/muq/__init__.py
src/muq/muq/muq.py
src/muq/muq/models/__init__.py
src/muq/muq/models/muq_model.py
src/muq/muq/modules/__init__.py
src/muq/muq/modules/conv.py
src/muq/muq/modules/features.py
src/muq/muq/modules/flash_conformer.py
src/muq/muq/modules/random_quantizer.py
src/muq/muq/modules/rvq.py
src/muq/muq_mulan/__init__.py
src/muq/muq_mulan/muq_mulan.py
src/muq/muq_mulan/models/__init__.py
src/muq/muq_mulan/models/audio.py
src/muq/muq_mulan/models/mulan.py
src/muq/muq_mulan/models/text.py
src/muq/muq_mulan/modules/__init__.py
src/muq/muq_mulan/modules/contrastive.py
src/muq/muq_mulan/modules/distributed.py
src/muq/muq_mulan/modules/extend_distributed.py
src/muq/muq_mulan/modules/transformer.py
src/muq/muq_mulan/modules/utils.py