Metadata-Version: 2.1
Name: muq
Version: 0.1.0
Summary: MuQ: A deep learning model for music and text
Home-page: https://github.com/tencent-ailab/MuQ
Author: Haina Zhu
Author-email: juhayna@qq.com
Classifier: Programming Language :: Python :: 3
Classifier: License :: OSI Approved :: MIT License
Classifier: Operating System :: OS Independent
Requires-Python: >=3.8
License-File: LICENSE
License-File: LICENSE_weights
